tmsproviderapisdk/__init__.py
tmsproviderapisdk/tms_account.py
tmsproviderapisdk/tms_account_network.py
tmsproviderapisdk/tms_account_subscription.py
tmsproviderapisdk/tms_base_model.py
tmsproviderapisdk/tms_channel.py
tmsproviderapisdk/tms_config.py
tmsproviderapisdk/tms_device.py
tmsproviderapisdk/tms_device_subscription.py
tmsproviderapisdk/tms_devices_types.py
tmsproviderapisdk/tms_exceptions.py
tmsproviderapisdk/tms_extended_model.py
tmsproviderapisdk/tms_provider.py
tmsproviderapisdk/tms_region.py
tmsproviderapisdk/tms_tarif.py
tmsproviderapisdk/tms_tarif_tag.py
tmsproviderapisdk-0.1.3.data/data/LICENSE
tmsproviderapisdk-0.1.3.dist-info/LICENSE
tmsproviderapisdk-0.1.3.dist-info/METADATA
tmsproviderapisdk-0.1.3.dist-info/WHEEL
tmsproviderapisdk-0.1.3.dist-info/top_level.txt
tmsproviderapisdk-0.1.3.dist-info/RECORD
