Metadata-Version: 2.1
Name: tmsproviderapisdk
Version: 0.1.3
Summary: TVIP TMS provider api sdk
Home-page: https://github.com/tvip/tmsproviderapisdk
Author: Tvip
Author-email: td@tvip.ru
Classifier: Programming Language :: Python :: 3
Classifier: License :: OSI Approved :: MIT License
Classifier: Operating System :: OS Independent
Requires-Python: >=3.6
License-File: LICENSE
